{
    "id": "1769314795",
    "name": "תנועות עוש יעקב פועלים מ25/11 עד היום",
    "column_values": [
        {
            "column": {
                "title": "בטיפול",
                "id": "people__1"
            },
            "text": "רוזי יוסף",
            "value": "{\"changed_at\":\"2025-01-09T10:28:14.402Z\",\"personsAndTeams\":[{\"id\":68720225,\"kind\":\"person\"}]}"
        },
        {
            "column": {
                "title": "סטטוס סאבים",
                "id": "status"
            },
            "text": "תקין",
            "value": "{\"index\":1,\"post_id\":null,\"changed_at\":\"2025-01-12T08:20:29.432Z\"}"
        },
        {
            "column": {
                "title": "ציר זמן",
                "id": "timeline3__1"
            },
            "text": "",
            "value": null
        },
        {
            "column": {
                "title": "קבצים",
                "id": "files__1"
            },
            "text": "https://baroffice11s-team.monday.com/protected_static/26576015/resources/90376076/%D7%AA%D7%A0%D7%95%D7%A2%D7%95%D7%AA%20%D7%A2%D7%95%D7%A9%20%D7%99%D7%A2%D7%A7%D7%91%20%D7%A4%D7%95%D7%A2%D7%9C%D7%99%D7%9D%20%D7%9E2511%20%D7%A2%D7%93%20%D7%94%D7%99%D7%95%D7%9D.pdf",
            "value": "{\"files\":[{\"name\":\"תנועות עוש יעקב פועלים מ2511 עד היום.pdf\",\"assetId\":90376076,\"isImage\":\"false\",\"fileType\":\"ASSET\",\"createdAt\":1736670036605,\"createdBy\":\"68720225\"}]}"
        },
        {
            "column": {
                "title": "תאריך",
                "id": "date__1"
            },
            "text": "2025-01-12",
            "value": "{\"date\":\"2025-01-12\",\"changed_at\":\"2025-01-12T08:20:31.113Z\"}"
        },
        {
            "column": {
                "title": "Date",
                "id": "date_mkmcxhj7"
            },
            "text": "",
            "value": null
        },
        {
            "column": {
                "title": "Item ID",
                "id": "item_id_Mjj6mEi1"
            },
            "text": "1769314795",
            "value": "{\"item_id\":\"1769314795\"}"
        }
    ],
    "assets": [
        {
            "name": "תנועות עוש יעקב פועלים מ2511 עד היום.pdf",
            "public_url": "https://prod-euc1-files-monday-com.s3.eu-central-1.amazonaws.com/26576015/resources/90376076/%D7%AA%D7%A0%D7%95%D7%A2%D7%95%D7%AA%20%D7%A2%D7%95%D7%A9%20%D7%99%D7%A2%D7%A7%D7%91%20%D7%A4%D7%95%D7%A2%D7%9C%D7%99%D7%9D%20%D7%9E2511%20%D7%A2%D7%93%20%D7%94%D7%99%D7%95%D7%9D.pdf?response-content-disposition=attachment&X-Amz-Algorithm=AWS4-HMAC-SHA256&X-Amz-Credential=AKIA4MPVJMFXJ4YPAV7U%2F20250214%2Feu-central-1%2Fs3%2Faws4_request&X-Amz-Date=20250214T161538Z&X-Amz-Expires=3600&X-Amz-SignedHeaders=host&X-Amz-Signature=5ddf0055b1f06527fbd838d094a1acf5baa44b680ea75047a90d8ac8b921000f"
        }
    ]
}